san_log_sdk/__init__.py
san_log_sdk/client.py
san_log_sdk/parser.py
san_log_sdk/server.py
san_log_sdk/sj_sdk.py
san_log_sdk/test_request.py
san_log_sdk/threaded_handler.py
san_log_sdk-0.1.1.dist-info/LICENCE
san_log_sdk-0.1.1.dist-info/METADATA
san_log_sdk-0.1.1.dist-info/WHEEL
san_log_sdk-0.1.1.dist-info/RECORD
