Metadata-Version: 2.1
Name: san-log-sdk
Version: 0.1.1
Summary: Simple SDK to share logs and overal status
Home-page: https://bitbucket.org/sanjorgedev/san_logs_sdk/src/
License: LICENSE
Author: Automóviles San Jorge
Author-email: backup@sanjorge-sa.com.ar
Requires-Python: >=3.12,<4.0
Classifier: License :: Other/Proprietary License
Classifier: Programming Language :: Python :: 3
Classifier: Programming Language :: Python :: 3.12
Project-URL: Repository, https://bitbucket.org/sanjorgedev/san_logs_sdk/src/
